gmltools/To_Do.txt
gmltools/__init__.py
gmltools/eda/__init__.py
gmltools/eda/eda.py
gmltools/model_prediction/__init__.py
gmltools/model_prediction/_forecast.py
gmltools/model_selection/__init__.py
gmltools/model_selection/_scorer.py
gmltools/model_selection/_search.py
gmltools/models/__init__.py
gmltools/models/bayes.py
gmltools/models/custom_scorings.py
gmltools/models/dummy_model.py
gmltools/models/model.py
gmltools/models/model_.py
gmltools/models/models_info.py
gmltools/models/montecarlo.py
gmltools/models/timeseriesplit.py
gmltools/models_analysis/__init__.py
gmltools/models_analysis/classification_analysis.py
gmltools/models_analysis/xai.py
gmltools/preprocess/__init__.py
gmltools/preprocess/autoregressive_features.py
gmltools/preprocess/manage_holidays.py
gmltools/preprocess/preprocess.py
gmltools-0.1.40.dist-info/LICENSE
gmltools-0.1.40.dist-info/METADATA
gmltools-0.1.40.dist-info/WHEEL
gmltools-0.1.40.dist-info/top_level.txt
gmltools-0.1.40.dist-info/RECORD
