Metadata-Version: 2.1
Name: gmltools
Version: 0.1.40
Summary: Machine Learning library aiming for a higher level programming, organizing best tools
Author: Diego Sanz-Gadea Sánchez
Author-email: dsanzgadeasanchez@gmail.com
Requires-Python: >=3.8,<4.0
License-File: LICENSE
Requires-Dist: matplotlib (<4.0.0,>=3.6.3)
Requires-Dist: numpy (<2.0.0,>=1.21.6)
Requires-Dist: pandas (<2.0.0,>=1.5.0)
Requires-Dist: xgboost (==1.5.0)
Requires-Dist: lightgbm (>=3.3.5)
Requires-Dist: linear-tree (>=0.3.5)
Requires-Dist: scikit-learn (>=1.2.1)
